{
  "exec": "npm run dev",
  "identity": {
    "file_count": 1627,
    "mutable_files": [],
    "root_hash": [
      79,
      156,
      65,
      158,
      113,
      228,
      11,
      46,
      251,
      229,
      96,
      57,
      59,
      61,
      254,
      252,
      220,
      69,
      142,
      183,
      17,
      21,
      220,
      212,
      54,
      55,
      54,
      173,
      135,
      99,
      99,
      17
    ]
  },
  "sealed": true,
  "timestamp": "2026-01-21T11:39:29.654708035+00:00",
  "version": "1.0.0"
}